{
  "risk_capture_verification_activities": [
    {
      "id": "550e8400-e29b-41d4-a716-446655451001",
      "risk_capture_id": "550e8400-e29b-41d4-a716-446655443001",
      "verifier_id": "550e8400-e29b-41d4-a716-446655445010",
      "activity_type": "assigned",
      "description": "Risk capture verification assigned for Sistem ERP Perusahaan",
      "old_status": null,
      "new_status": "submitted",
      "risks_verified": 0,
      "total_risks": 8,
      "notes": "Initial assignment for comprehensive ERP risk assessment",
      "activity_at": "2024-01-22T12:00:00Z",
      "created_at": "2024-01-22T12:00:00Z",
      "verifier_name": "Chief Risk Officer",
      "project_name": "Sistem ERP Perusahaan"
    },
    {
      "id": "550e8400-e29b-41d4-a716-446655451002",
      "risk_capture_id": "550e8400-e29b-41d4-a716-446655443001",
      "verifier_id": "550e8400-e29b-41d4-a716-446655445010",
      "activity_type": "started_review",
      "description": "Started reviewing ERP risk capture assessment",
      "old_status": "submitted",
      "new_status": "under_review",
      "risks_verified": 0,
      "total_risks": 8,
      "notes": "Beginning detailed review of identified risks",
      "activity_at": "2024-01-22T14:00:00Z",
      "created_at": "2024-01-22T14:00:00Z",
      "verifier_name": "Chief Risk Officer",
      "project_name": "Sistem ERP Perusahaan"
    },
    {
      "id": "550e8400-e29b-41d4-a716-446655451003",
      "risk_capture_id": "550e8400-e29b-41d4-a716-446655443001",
      "verifier_id": "550e8400-e29b-41d4-a716-446655445010",
      "activity_type": "risk_verified",
      "description": "Verified data security risks",
      "old_status": "under_review",
      "new_status": "under_review",
      "risks_verified": 2,
      "total_risks": 8,
      "notes": "Data security and backup controls are adequate",
      "activity_at": "2024-01-22T15:30:00Z",
      "created_at": "2024-01-22T15:30:00Z",
      "verifier_name": "Chief Risk Officer",
      "project_name": "Sistem ERP Perusahaan"
    },
    {
      "id": "550e8400-e29b-41d4-a716-446655451004",
      "risk_capture_id": "550e8400-e29b-41d4-a716-446655443001",
      "verifier_id": "550e8400-e29b-41d4-a716-446655445010",
      "activity_type": "comment_added",
      "description": "Added comments on integration risks",
      "old_status": "under_review",
      "new_status": "under_review",
      "risks_verified": 4,
      "total_risks": 8,
      "notes": "Integration testing protocols need strengthening",
      "activity_at": "2024-01-22T16:45:00Z",
      "created_at": "2024-01-22T16:45:00Z",
      "verifier_name": "Chief Risk Officer",
      "project_name": "Sistem ERP Perusahaan"
    },
    {
      "id": "550e8400-e29b-41d4-a716-446655451005",
      "risk_capture_id": "550e8400-e29b-41d4-a716-446655443002",
      "verifier_id": "550e8400-e29b-41d4-a716-446655445010",
      "activity_type": "assigned",
      "description": "Risk capture verification assigned for Mobile Banking App",
      "old_status": null,
      "new_status": "submitted",
      "risks_verified": 0,
      "total_risks": 6,
      "notes": "Urgent security-focused risk review required",
      "activity_at": "2024-01-26T16:00:00Z",
      "created_at": "2024-01-26T16:00:00Z",
      "verifier_name": "Chief Risk Officer",
      "project_name": "Mobile Banking App"
    },
    {
      "id": "550e8400-e29b-41d4-a716-446655451006",
      "risk_capture_id": "550e8400-e29b-41d4-a716-446655443002",
      "verifier_id": "550e8400-e29b-41d4-a716-446655445010",
      "activity_type": "started_review",
      "description": "Started urgent review of mobile banking risks",
      "old_status": "submitted",
      "new_status": "under_review",
      "risks_verified": 0,
      "total_risks": 6,
      "notes": "Fast-track security assessment initiated",
      "activity_at": "2024-01-26T16:30:00Z",
      "created_at": "2024-01-26T16:30:00Z",
      "verifier_name": "Chief Risk Officer",
      "project_name": "Mobile Banking App"
    },
    {
      "id": "550e8400-e29b-41d4-a716-446655451007",
      "risk_capture_id": "550e8400-e29b-41d4-a716-446655443002",
      "verifier_id": "550e8400-e29b-41d4-a716-446655445010",
      "activity_type": "risk_verified",
      "description": "Verified all security and authentication risks",
      "old_status": "under_review",
      "new_status": "under_review",
      "risks_verified": 6,
      "total_risks": 6,
      "notes": "All security controls properly implemented and documented",
      "activity_at": "2024-01-27T09:30:00Z",
      "created_at": "2024-01-27T09:30:00Z",
      "verifier_name": "Chief Risk Officer",
      "project_name": "Mobile Banking App"
    },
    {
      "id": "550e8400-e29b-41d4-a716-446655451008",
      "risk_capture_id": "550e8400-e29b-41d4-a716-446655443002",
      "verifier_id": "550e8400-e29b-41d4-a716-446655445010",
      "activity_type": "verification_completed",
      "description": "Completed mobile banking risk verification",
      "old_status": "under_review",
      "new_status": "verified",
      "risks_verified": 6,
      "total_risks": 6,
      "notes": "Comprehensive risk mitigation strategies approved",
      "activity_at": "2024-01-27T10:45:00Z",
      "created_at": "2024-01-27T10:45:00Z",
      "verifier_name": "Chief Risk Officer",
      "project_name": "Mobile Banking App"
    },
    {
      "id": "550e8400-e29b-41d4-a716-446655451009",
      "risk_capture_id": "550e8400-e29b-41d4-a716-446655443002",
      "verifier_id": "550e8400-e29b-41d4-a716-446655445010",
      "activity_type": "approved",
      "description": "Final approval for mobile banking risk assessment",
      "old_status": "verified",
      "new_status": "verified",
      "risks_verified": 6,
      "total_risks": 6,
      "notes": "Risk assessment meets regulatory standards for financial services",
      "activity_at": "2024-01-27T10:45:00Z",
      "created_at": "2024-01-27T10:45:00Z",
      "verifier_name": "Chief Risk Officer",
      "project_name": "Mobile Banking App"
    },
    {
      "id": "550e8400-e29b-41d4-a716-446655451010",
      "risk_capture_id": "550e8400-e29b-41d4-a716-446655443004",
      "verifier_id": "550e8400-e29b-41d4-a716-446655445011",
      "activity_type": "assigned",
      "description": "Risk capture verification assigned for E-commerce Platform",
      "old_status": null,
      "new_status": "submitted",
      "risks_verified": 0,
      "total_risks": 5,
      "notes": "E-commerce security and payment risk assessment",
      "activity_at": "2024-01-19T10:00:00Z",
      "created_at": "2024-01-19T10:00:00Z",
      "verifier_name": "Senior Risk Analyst",
      "project_name": "E-commerce Platform"
    },
    {
      "id": "550e8400-e29b-41d4-a716-446655451011",
      "risk_capture_id": "550e8400-e29b-41d4-a716-446655443004",
      "verifier_id": "550e8400-e29b-41d4-a716-446655445011",
      "activity_type": "started_review",
      "description": "Started reviewing e-commerce platform risks",
      "old_status": "submitted",
      "new_status": "under_review",
      "risks_verified": 0,
      "total_risks": 5,
      "notes": "Focus on payment security and data protection",
      "activity_at": "2024-01-19T11:00:00Z",
      "created_at": "2024-01-19T11:00:00Z",
      "verifier_name": "Senior Risk Analyst",
      "project_name": "E-commerce Platform"
    },
    {
      "id": "550e8400-e29b-41d4-a716-446655451012",
      "risk_capture_id": "550e8400-e29b-41d4-a716-446655443004",
      "verifier_id": "550e8400-e29b-41d4-a716-446655445011",
      "activity_type": "revision_requested",
      "description": "Revision requested for payment security measures",
      "old_status": "under_review",
      "new_status": "needs_revision",
      "risks_verified": 3,
      "total_risks": 5,
      "notes": "Payment security controls require additional strengthening before approval",
      "activity_at": "2024-01-20T14:30:00Z",
      "created_at": "2024-01-20T14:30:00Z",
      "verifier_name": "Senior Risk Analyst",
      "project_name": "E-commerce Platform"
    }
  ]
}
